{"namedChunkGroups":{"polyfill":{"name":"polyfill","assets":[{"name":"webpack-runtime-740e8193c1e62ba1b0ff.js","size":5174},{"name":"polyfill-5c6a5f5a78b8fa2f4991.js","size":82206}],"filteredAssets":0,"assetsSize":87380,"filteredAuxiliaryAssets":2,"auxiliaryAssetsSize":220508},"app":{"name":"app","assets":[{"name":"webpack-runtime-740e8193c1e62ba1b0ff.js","size":5174},{"name":"styles.63fc8bf89bdcde78c26e.css","size":9051},{"name":"framework-c4b9952841844d9091bc.js","size":128971},{"name":"app-a8884eb60055e88148a3.js","size":69144}],"filteredAssets":0,"assetsSize":212340,"filteredAuxiliaryAssets":5,"auxiliaryAssetsSize":703451},"component---src-pages-404-js":{"name":"component---src-pages-404-js","assets":[{"name":"styles.63fc8bf89bdcde78c26e.css","size":9051},{"name":"d7eeaac4-c520de9466ee4c766db4.js","size":1862},{"name":"commons-c82c16030ed695ce77c1.js","size":20114},{"name":"component---src-pages-404-js-a421893ee9132fd5047c.js","size":550}],"filteredAssets":0,"assetsSize":31577,"filteredAuxiliaryAssets":6,"auxiliaryAssetsSize":925871},"component---src-pages-index-js":{"name":"component---src-pages-index-js","assets":[{"name":"styles.63fc8bf89bdcde78c26e.css","size":9051},{"name":"d7eeaac4-c520de9466ee4c766db4.js","size":1862},{"name":"commons-c82c16030ed695ce77c1.js","size":20114},{"name":"component---src-pages-index-js-2bcf9590c67b24395cec.js","size":1408}],"filteredAssets":0,"assetsSize":32435,"filteredAuxiliaryAssets":6,"auxiliaryAssetsSize":928313},"component---src-pages-privacy-tsx":{"name":"component---src-pages-privacy-tsx","assets":[{"name":"styles.63fc8bf89bdcde78c26e.css","size":9051},{"name":"d7eeaac4-c520de9466ee4c766db4.js","size":1862},{"name":"commons-c82c16030ed695ce77c1.js","size":20114},{"name":"component---src-pages-privacy-tsx-42dc0028c993421a4ecd.js","size":7369}],"filteredAssets":0,"assetsSize":38396,"filteredAuxiliaryAssets":6,"auxiliaryAssetsSize":934543},"component---src-pages-termsandconditions-tsx":{"name":"component---src-pages-termsandconditions-tsx","assets":[{"name":"styles.63fc8bf89bdcde78c26e.css","size":9051},{"name":"d7eeaac4-c520de9466ee4c766db4.js","size":1862},{"name":"commons-c82c16030ed695ce77c1.js","size":20114},{"name":"component---src-pages-termsandconditions-tsx-2fe62d61b9144f0c022d.js","size":6926}],"filteredAssets":0,"assetsSize":37953,"filteredAuxiliaryAssets":6,"auxiliaryAssetsSize":933980},"component---src-templates-blog-post-js":{"name":"component---src-templates-blog-post-js","assets":[{"name":"styles.63fc8bf89bdcde78c26e.css","size":9051},{"name":"d7eeaac4-c520de9466ee4c766db4.js","size":1862},{"name":"commons-c82c16030ed695ce77c1.js","size":20114},{"name":"component---src-templates-blog-post-js-2995496666fa3e9d608d.js","size":1334}],"filteredAssets":0,"assetsSize":32361,"filteredAuxiliaryAssets":6,"auxiliaryAssetsSize":928555}},"assetsByChunkName":{"polyfill":["webpack-runtime-740e8193c1e62ba1b0ff.js","polyfill-5c6a5f5a78b8fa2f4991.js"],"app":["webpack-runtime-740e8193c1e62ba1b0ff.js","styles.63fc8bf89bdcde78c26e.css","framework-c4b9952841844d9091bc.js","app-a8884eb60055e88148a3.js"],"component---src-pages-404-js":["styles.63fc8bf89bdcde78c26e.css","d7eeaac4-c520de9466ee4c766db4.js","commons-c82c16030ed695ce77c1.js","component---src-pages-404-js-a421893ee9132fd5047c.js"],"component---src-pages-index-js":["styles.63fc8bf89bdcde78c26e.css","d7eeaac4-c520de9466ee4c766db4.js","commons-c82c16030ed695ce77c1.js","component---src-pages-index-js-2bcf9590c67b24395cec.js"],"component---src-pages-privacy-tsx":["styles.63fc8bf89bdcde78c26e.css","d7eeaac4-c520de9466ee4c766db4.js","commons-c82c16030ed695ce77c1.js","component---src-pages-privacy-tsx-42dc0028c993421a4ecd.js"],"component---src-pages-termsandconditions-tsx":["styles.63fc8bf89bdcde78c26e.css","d7eeaac4-c520de9466ee4c766db4.js","commons-c82c16030ed695ce77c1.js","component---src-pages-termsandconditions-tsx-2fe62d61b9144f0c022d.js"],"component---src-templates-blog-post-js":["styles.63fc8bf89bdcde78c26e.css","d7eeaac4-c520de9466ee4c766db4.js","commons-c82c16030ed695ce77c1.js","component---src-templates-blog-post-js-2995496666fa3e9d608d.js"]},"childAssetsByChunkName":{}}